aiokubemq/__init__.py
aiokubemq/client.py
aiokubemq/enums.py
aiokubemq/requests.py
aiokubemq/types.py
aiokubemq/proto/__init__.py
aiokubemq/proto/kubemq_pb2.py
aiokubemq/proto/kubemq_pb2.pyi
aiokubemq/proto/kubemq_pb2_grpc.py
aiokubemq-0.1.1.dist-info/LICENSE
aiokubemq-0.1.1.dist-info/METADATA
aiokubemq-0.1.1.dist-info/WHEEL
aiokubemq-0.1.1.dist-info/top_level.txt
aiokubemq-0.1.1.dist-info/RECORD
