Metadata-Version: 2.1
Name: aiokubemq
Version: 0.1.1
Summary: Asynchronous KubeMQ Client
Home-page: https://gitlab.com/TECHNOFAB/aiokubemq
Author: Technofab
Author-email: aiokubemq.git@technofab.de
License: GPL-3.0
Platform: UNKNOWN
Classifier: Development Status :: 3 - Alpha
Classifier: Intended Audience :: Developers
Classifier: License :: OSI Approved :: GNU General Public License v3 (GPLv3)
Classifier: Natural Language :: English
Classifier: Operating System :: OS Independent
Classifier: Programming Language :: Python :: 3.6
Classifier: Programming Language :: Python :: 3.7
Classifier: Programming Language :: Python :: 3.8
Classifier: Programming Language :: Python :: 3.9
Classifier: Topic :: Software Development :: Libraries
Classifier: Topic :: Software Development :: Libraries :: Python Modules
Classifier: Topic :: Utilities
Classifier: Typing :: Typed
Requires-Python: >=3.6
License-File: LICENSE
Requires-Dist: grpcio (~=1.43.0)
Requires-Dist: protobuf (~=3.19.3)
